{
  "cities": [
    {
      "vaccine_available": "true",
      "name": "Ahmedabad",
      "id": "1"
    },
    {
      "vaccine_available": "true",
      "name": "Bengaluru",
      "id": "2"
    },
    {
      "name": "Chennai",
      "vaccine_available": "false",
      "id": "3"
    },
    {
      "name": "Delhi",
      "vaccine_available": "true",
      "id": "4"
    },
    {
      "name": "Hyderabad",
      "vaccine_available": "true",
      "id": "5"
    },
    {
      "name": "Kolkata",
      "vaccine_available": "true",
      "id": "6"
    },
    {
      "name": "Mumbai",
      "vaccine_available": "true",
      "id": "7"
    },
    {
      "name": "Pune",
      "vaccine_available": "true",
      "id": "8"
    }
  ],
  "vacDetails": {
    "noOfVacComp": "15",
    "noOfRegs": 21,
    "totalNoOfVac": "390",
    "noOfVacRemaining": 4985,
    "noOfCities": 8
  },
  "users": [
    {
      "email": "vamsikrishna@123.com",
      "password": "Vamsi@123",
      "username": "vamsi krishna chebrolu",
      "confirmPassword": "Vamsi@123",
      "age": 23,
      "phone": 9390647765,
      "isAdmin": "false",
      "fathername": "Ramesh",
      "mothername": "madhavi",
      "fatherAge": 50,
      "motherAge": 42,
      "userSlotBooked": "yes",
      "userSlotDate": "2023-02-15",
      "userSlotTime": "02 PM",
      "userSlotLocation": "Bangalore",
      "fatherSlotBooked": "yes",
      "fatherSlotDate": "2023-02-15",
      "fatherSlotTime": "02 PM",
      "fatherSlotLocation": "Bangalore",
      "motherSlotBooked": "yes",
      "motherSlotDate": "2023-02-15",
      "motherSlotTime": "02 PM",
      "motherrSlotLocation": "Bangalore",
      "userVacStatus": "yes",
      "fatherVacStatus": "yes",
      "motherVacStatus": "yes",
      "address": "28-3-241,Maruthi nagar road-1,mypadu gate, Hyderabad",
      "id": 1
    },
    {
      "username": "kapil sharma",
      "email": "kapil@sharma.com",
      "password": "Kapil@123",
      "age": "20",
      "phone": "1231234567",
      "fathername": "kapil dev",
      "mothername": "kapil devi",
      "fatherAge": 45,
      "motherAge": "40",
      "isAdmin": "false",
      "userSlotBooked": "no",
      "userSlotDate": "2023-08-16",
      "userSlotTime": "11 AM",
      "userSlotLocation": "Chennai",
      "fatherSlotBooked": "yes",
      "fatherSlotDate": "2023-09-01",
      "fatherSlotTime": "09 AM",
      "fatherSlotLocation": "Bengaluru",
      "motherSlotBooked": "yes",
      "motherSlotDate": "2023-09-01",
      "motherSlotTime": "11 AM",
      "motherSlotLocation": "Ahmedabad",
      "userVacStatus": "no",
      "fatherVacStatus": "yes",
      "motherVacStatus": "yes",
      "address": "28-3-241,Mphasis office, kharadi, pune",
      "confirmPassword": "Kapil@123",
      "id": 2,
      "motherName": "kapil deviA",
      "mobileNumber": "",
      "fatherName": "kapil de"
    },
    {
      "email": "Aaditri@123.com",
      "password": "Aaditri@000",
      "username": "Aaditri Rao",
      "confirmPassword": "Aaditri@000",
      "age": 22,
      "phone": 9246789342,
      "isAdmin": "false",
      "fathername": "Suresh",
      "mothername": "Lakshmi",
      "fatherAge": 52,
      "motherAge": 45,
      "userSlotBooked": "no",
      "userSlotDate": "2023-02-16",
      "userSlotTime": "10 AM",
      "userSlotLocation": "Hyderabad",
      "fatherSlotBooked": "yes",
      "fatherSlotDate": "2023-02-16",
      "fatherSlotTime": "10 AM",
      "fatherSlotLocation": "Hyderabad",
      "motherSlotBooked": "yes",
      "motherSlotDate": "2023-02-16",
      "motherSlotTime": "10 AM",
      "userVacStatus": "yes",
      "fatherVacStatus": "yes",
      "motherVacStatus": "yes",
      "address": "30-5-265, Geetha Nagar road-1, Hyderabad",
      "id": 3
    },
    {
      "email": "Bhanu@123.com",
      "password": "Bhanu@123",
      "username": "Bhanu Prakash",
      "confirmPassword": "Bhanu@123",
      "age": 22,
      "phone": 9246789367,
      "isAdmin": "false",
      "fathername": "Rakesh",
      "mothername": "Latha",
      "fatherAge": 50,
      "motherAge": 43,
      "userSlotBooked": "yes",
      "userSlotDate": "2023-02-24",
      "userSlotTime": "01 PM",
      "userSlotLocation": "Chennai",
      "fatherSlotBooked": "yes",
      "fatherSlotDate": "2023-02-24",
      "fatherSlotTime": "01 PM",
      "fatherSlotLocation": "Chennai",
      "motherSlotBooked": "yes",
      "motherSlotDate": "2023-02-24",
      "motherSlotTime": "01 PM",
      "motherSlotLocation": "Chennai",
      "userVacStatus": "yes",
      "fatherVacStatus": "yes",
      "motherVacStatus": "yes",
      "address": "30-6-263, Geetha Nagar road-1, Hyderabad",
      "id": 4
    },
    {
      "email": "Akshay@123.com",
      "password": "Akshay@123",
      "username": "Akshay Kumar",
      "confirmPassword": "Akshay@123",
      "age": 23,
      "phone": 9246789553,
      "isAdmin": "false",
      "fathername": "Raghav",
      "mothername": "Rama",
      "fatherAge": 51,
      "motherAge": 44,
      "userSlotBooked": "yes",
      "userSlotDate": "2023-02-26",
      "userSlotTime": "11 AM",
      "userSlotLocation": "Pune",
      "fatherSlotBooked": "yes",
      "fatherSlotDate": "2023-02-26",
      "fatherSlotTime": "11 AM",
      "fatherSlotLocation": "Pune",
      "motherSlotBooked": "yes",
      "motherSlotDate": "2023-02-26",
      "motherSlotTime": "11 AM",
      "motherSlotLocation": "Pune",
      "userVacStatus": "yes",
      "fatherVacStatus": "yes",
      "motherVacStatus": "yes",
      "address": "30-6-268, Geetha Nagar road-2, Hyderabad",
      "id": 5
    },
    {
      "username": "Eshita Roy",
      "email": "Eshita@234.com",
      "password": "Eshita@123",
      "age": 25,
      "phone": 9912356879,
      "fathername": "Gaurav",
      "mothername": "rama devi",
      "fatherAge": 59,
      "motherAge": 50,
      "address": "28-4-242,Geeta nagar road-1,mypadu gate",
      "isAdmin": "false",
      "userSlotBooked": "no",
      "userSlotDate": "null",
      "userSlotTime": "null",
      "userSlotLocation": "null",
      "fatherSlotBooked": "no",
      "fatherSlotDate": "null",
      "fatherSlotTime": "null",
      "fatherSlotLocation": "null",
      "motherSlotBooked": "no",
      "motherSlotDate": "null",
      "motherSlotTime": "null",
      "motherSlotLocation": "null",
      "userVacStatus": "no",
      "fatherVacStatus": "no",
      "motherVacStatus": "no",
      "confirmPassword": "Eshita@123",
      "id": 6
    },
    {
      "username": "Gaurav sharma",
      "email": "Gaurav@sharma.com",
      "password": "Gaurav@123",
      "age": 27,
      "phone": 6549856879,
      "fathername": "Raghav",
      "mothername": "Malini",
      "fatherAge": 55,
      "motherAge": 50,
      "address": "29-3-243,Ram nagar road-1,Secunderabad",
      "isAdmin": "false",
      "userSlotBooked": "no",
      "userSlotDate": "null",
      "userSlotTime": "null",
      "userSlotLocation": "null",
      "fatherSlotBooked": "no",
      "fatherSlotDate": "null",
      "fatherSlotTime": "null",
      "fatherSlotLocation": "null",
      "motherSlotBooked": "no",
      "motherSlotDate": "null",
      "motherSlotTime": "null",
      "motherSlotLocation": "null",
      "userVacStatus": "no",
      "fatherVacStatus": "no",
      "motherVacStatus": "no",
      "confirmPassword": "Gaurav@123",
      "id": 7
    },
    {
      "email": "Prakash@123.com",
      "password": "Prakash@123",
      "username": "Prakash Kumar",
      "confirmPassword": "Prakash@123",
      "age": 30,
      "phone": 6305789553,
      "isAdmin": "false",
      "fathername": "Gaurav",
      "mothername": "Rama Devi",
      "fatherAge": 60,
      "motherAge": 55,
      "userSlotBooked": "yes",
      "userSlotDate": "2023-03-29",
      "userSlotTime": "12 PM",
      "userSlotLocation": "Noida",
      "fatherSlotBooked": "yes",
      "fatherSlotDate": "2023-03-29",
      "fatherSlotTime": "12 PM",
      "fatherSlotLocation": "Noida",
      "motherSlotBooked": "yes",
      "motherSlotDate": "2023-03-29",
      "motherSlotTime": "12 PM",
      "motherSlotLocation": "Noida",
      "userVacStatus": "yes",
      "fatherVacStatus": "yes",
      "motherVacStatus": "yes",
      "address": "30-5-267, Ram Nagar road-2, Secunderabad",
      "id": 8
    },
    {
      "email": "Mary@123.com",
      "password": "Mary@123",
      "username": "Mary Ray",
      "confirmPassword": "Mary@123",
      "age": 23,
      "phone": 9246888553,
      "isAdmin": "false",
      "fathername": "Aaron",
      "mothername": "Ester",
      "fatherAge": 52,
      "motherAge": 45,
      "userSlotBooked": "yes",
      "userSlotDate": "2023-02-27",
      "userSlotTime": "03 PM",
      "userSlotLocation": "Mumbai",
      "fatherSlotBooked": "yes",
      "fatherSlotDate": "2023-02-27",
      "fatherSlotTime": "03 PM",
      "fatherSlotLocation": "Mumbai",
      "motherSlotBooked": "yes",
      "motherSlotDate": "2023-02-27",
      "motherSlotTime": "03 PM",
      "motherSlotLocation": "Mumbai",
      "userVacStatus": "yes",
      "fatherVacStatus": "yes",
      "motherVacStatus": "yes",
      "address": "30-8-261, Ram Nagar road-2, Secunderabad",
      "id": 9
    },
    {
      "username": "Aditya sharma",
      "email": "Aditya@sharma.com",
      "password": "Aditya@123",
      "age": 25,
      "phone": 6542356304,
      "fathername": "kapil sharma",
      "mothername": "kapil devi",
      "fatherAge": 60,
      "motherAge": 50,
      "address": "28-3-242,Nagaram road-1,cheeryal",
      "isAdmin": "false",
      "userSlotBooked": "yes",
      "userSlotDate": "2023-07-29",
      "userSlotTime": "11:30 AM",
      "userSlotLocation": "Hyderabad",
      "fatherSlotBooked": "yes",
      "fatherSlotDate": "2023-07-29",
      "fatherSlotTime": "11:30 AM",
      "fatherSlotLocation": "Hyderabad",
      "motherSlotBooked": "yes",
      "motherSlotDate": "2023-07-29",
      "motherSlotTime": "11:30 AM",
      "motherSlotLocation": "Hyderabad",
      "userVacStatus": "no",
      "fatherVacStatus": "no",
      "motherVacStatus": "no",
      "confirmPassword": "Aditya@123",
      "id": 10
    },
    {
      "username": "Grace",
      "email": "Grace@123.com",
      "password": "Grace@123",
      "age": 27,
      "phone": 6092356879,
      "fathername": "Harie",
      "mothername": "Marie",
      "fatherAge": 60,
      "motherAge": 50,
      "address": "29-3-241,Nagaram, cheeryal",
      "isAdmin": "false",
      "userSlotBooked": "yes",
      "userSlotDate": "2023-07-28",
      "userSlotTime": "09 AM",
      "userSlotLocation": "Bangalore",
      "fatherSlotBooked": "yes",
      "fatherSlotDate": "2023-07-28",
      "fatherSlotTime": "09 AM",
      "fatherSlotLocation": "Bangalore",
      "motherSlotBooked": "yes",
      "motherSlotDate": "2023-02-2",
      "motherSlotTime": "09 AM",
      "motherSlotLocation": "Bangalore",
      "userVacStatus": "no",
      "fatherVacStatus": "no",
      "motherVacStatus": "no",
      "confirmPassword": "Grace@123",
      "id": 11
    },
    {
      "username": "Rani sharma",
      "email": "Rani@sharma.com",
      "password": "Rani@123",
      "age": 26,
      "phone": 8002356879,
      "fathername": "Aditya Sharma",
      "mothername": "Aditi Sharma",
      "fatherAge": 55,
      "motherAge": 50,
      "address": "28-3-244,Nagaram road-1,Cheeryal",
      "isAdmin": "false",
      "userSlotBooked": "yes",
      "userSlotDate": "2023-08-20",
      "userSlotTime": "09 AM",
      "userSlotLocation": "Bengaluru",
      "fatherSlotBooked": "yes",
      "fatherSlotDate": "2023-07-30",
      "fatherSlotTime": "02:30 PM",
      "fatherSlotLocation": "Chennai",
      "motherSlotBooked": "yes",
      "motherSlotDate": "2023-07-30",
      "motherSlotTime": "02:30",
      "motherSlotLocation": "Chennai",
      "userVacStatus": "yes",
      "fatherVacStatus": "yes",
      "motherVacStatus": "yes",
      "confirmPassword": "Rani@123",
      "id": 12
    },
    {
      "email": "Murali@123.com",
      "password": "Murali@123",
      "username": "Murali Krishna",
      "confirmPassword": "Murali@123",
      "age": 23,
      "phone": 7770647765,
      "isAdmin": "false",
      "fathername": "Naresh",
      "mothername": "Rani",
      "fatherAge": 55,
      "motherAge": 49,
      "userSlotBooked": "yes",
      "userSlotDate": "2023-04-11",
      "fatherSlotBooked": "yes",
      "userSlotTime": "08 AM",
      "userSlotLocation": "Pune",
      "fatherSlotDate": "2023-04-11",
      "fatherSlotTime": "08 AM",
      "fatherSlotLocation": "Pune",
      "motherSlotBooked": "yes",
      "motherSlotDate": "2023-04-11",
      "motherSlotTime": "08 AM",
      "motherSlotLocation": "Pune",
      "userVacStatus": "yes",
      "fatherVacStatus": "yes",
      "motherVacStatus": "no",
      "address": "LIG-B-30, Radhika, Hyderabad",
      "id": 13
    },
    {
      "email": "Ramesh@123.com",
      "password": "Ramesh@123",
      "username": "Ramesh Kumar",
      "confirmPassword": "Ramesh@123",
      "age": 23,
      "phone": 9392227765,
      "isAdmin": "false",
      "fathername": "Naresh",
      "mothername": "madhavi",
      "fatherAge": 49,
      "motherAge": 43,
      "userSlotBooked": "yes",
      "userSlotDate": "2023-04-10",
      "userSlotTime": "08:30 AM",
      "userSlotLocation": "Noida",
      "fatherSlotBooked": "yes",
      "fatherSlotDate": "2023-04-10",
      "fatherSlotTime": "08:30 AM",
      "fatherSlotLocation": "Noida",
      "motherSlotBooked": "yes",
      "motherSlotDate": "2023-04-10",
      "motherSlotTime": "08:30 AM",
      "motherSlotLocation": "Noida",
      "userVacStatus": "yes",
      "fatherVacStatus": "yes",
      "motherVacStatus": "yes",
      "address": "LIG-B-24, Radhika, Hyderabad",
      "id": 14
    },
    {
      "email": "krishna@123.com",
      "password": "Krishna@123",
      "username": "Krishna kumar",
      "confirmPassword": "Krishna@123",
      "age": 23,
      "phone": 7900647765,
      "isAdmin": "false",
      "fathername": "Mahesh",
      "mothername": "madhuri",
      "fatherAge": 50,
      "motherAge": 42,
      "userSlotBooked": "yes",
      "userSlotDate": "2023-04-29",
      "userSlotTime": "08:15 AM",
      "userSlotLocation": "Mumbai",
      "fatherSlotBooked": "yes",
      "fatherSlotDate": "2023-04-29",
      "fatherSlotTime": "08:15 AM",
      "fatherSlotLocation": "Mumbai",
      "motherSlotBooked": "yes",
      "motherSlotDate": "2023-04-20",
      "motherSlotTime": "08:15 AM",
      "motherSlotLocation": "Mumbai",
      "userVacStatus": "yes",
      "fatherVacStatus": "yes",
      "motherVacStatus": "yes",
      "address": "LIG-B-29, Radhika, Hyderabad",
      "id": 15
    },
    {
      "email": "Teja@123.com",
      "password": "Teja@123",
      "username": "Teja Varma",
      "confirmPassword": "Teja@123",
      "age": 24,
      "phone": 8990644465,
      "isAdmin": "false",
      "fathername": "Ramesh",
      "mothername": "Rama",
      "fatherAge": 50,
      "motherAge": 42,
      "userSlotBooked": "yes",
      "userSlotDate": "2023-04-17",
      "userSlotTime": "08:45 AM",
      "userSlotLocation": "Bangalore",
      "fatherSlotBooked": "yes",
      "fatherSlotDate": "2023-04-17",
      "fatherSlotTime": "08:45 AM",
      "fatherSlotLocation": "Bangalore",
      "motherSlotBooked": "yes",
      "motherSlotDate": "2023-04-17",
      "motherSlotTime": "08:45 AM",
      "motherSlotLocation": "Bangalore",
      "userVacStatus": "yes",
      "fatherVacStatus": "yes",
      "motherVacStatus": "yes",
      "address": "LIG-B-26, Radhika, Hyderabad",
      "id": 16
    },
    {
      "email": "Aaradhya@123.com",
      "password": "Aaradhya@123",
      "username": "Aaradhya Sharma",
      "confirmPassword": "Aaradhya@123",
      "age": 21,
      "phone": 8990647765,
      "isAdmin": "false",
      "fathername": "Aditya",
      "mothername": "Rama",
      "fatherAge": 49,
      "motherAge": 43,
      "userSlotBooked": "yes",
      "userSlotDate": "2023-04-15",
      "userSlotTime": "09:15 AM",
      "userSlotLocation": "Hyderabad",
      "fatherSlotBooked": "yes",
      "fatherSlotDate": "2023-04-15",
      "fatherSlotTime": "09:15 AM",
      "fatherSlotLocation": "Hyderabad",
      "motherSlotBooked": "yes",
      "motherSlotDate": "2023-04-15",
      "motherSlotTime": "09:15 AM",
      "motherSlotLocation": "Hyderabad",
      "userVacStatus": "yes",
      "fatherVacStatus": "yes",
      "motherVacStatus": "yes",
      "address": "LIG-B-27, Radhika, Hyderabad",
      "id": 17
    },
    {
      "username": "Sai Ganesh",
      "email": "sai@123.com",
      "password": "Sai@123",
      "age": 29,
      "phone": 6542356879,
      "fathername": "Krishna",
      "mothername": "Kaveri",
      "fatherAge": 60,
      "motherAge": 50,
      "address": "30-256-29, Prem Nagar road no 1, Medchal",
      "isAdmin": "false",
      "userSlotBooked": "yes",
      "userSlotDate": "2023-07-31",
      "userSlotTime": "09:30 AM",
      "userSlotLocation": "Chennai",
      "fatherSlotBooked": "yes",
      "fatherSlotDate": "2023-07-31",
      "fatherSlotTime": "09:30 AM",
      "fatherSlotLocation": "Chennai",
      "motherSlotBooked": "yes",
      "motherSlotDate": "2023-07-31",
      "motherSlotTime": "09:30 AM",
      "motherSlotLocation": "Chennai",
      "userVacStatus": "no",
      "fatherVacStatus": "no",
      "motherVacStatus": "no",
      "confirmPassword": "Sai@123",
      "id": 18
    },
    {
      "username": "Amreen Shaik",
      "email": "Amreen@234.com",
      "password": "Amreen@123",
      "age": 35,
      "phone": 6542356879,
      "fathername": "Hassin",
      "mothername": "Sana",
      "fatherAge": 65,
      "motherAge": 55,
      "address": "30-256-27, Prem Nagar road no 2, Medchal",
      "isAdmin": "false",
      "userSlotBooked": "yes",
      "userSlotDate": "2023-06-12",
      "userSlotTime": "09:45 AM",
      "userSlotLocation": "Noida",
      "fatherSlotBooked": "yes",
      "fatherSlotDate": "2023-06-12",
      "fatherSlotTime": "09:45 AM",
      "fatherSlotLocation": "Noida",
      "motherSlotBooked": "yes",
      "motherSlotDate": "2023-06-12",
      "motherSlotTime": "09:45 AM",
      "motherSlotLocation": "Noida",
      "userVacStatus": "no",
      "fatherVacStatus": "no",
      "motherVacStatus": "no",
      "confirmPassword": "Amreen@123",
      "id": 19
    },
    {
      "username": "Hassin Shaik",
      "email": "hassin@123.com",
      "password": "Hassin@123",
      "age": 30,
      "phone": 6542356009,
      "fathername": "Akbar",
      "mothername": "Amreen",
      "fatherAge": 60,
      "motherAge": 50,
      "address": "30-256-29, Prem Nagar road no 1, Medchal",
      "isAdmin": "false",
      "userSlotBooked": "yes",
      "userSlotDate": "2023-06-10",
      "userSlotTime": "10:15 AM",
      "userSlotLocation": "Mumbai",
      "fatherSlotBooked": "yes",
      "fatherSlotDate": "2023-06-10",
      "fatherSlotTime": "10:15 AM",
      "fatherSlotLocation": "Mumbai",
      "motherSlotBooked": "yes",
      "motherSlotDate": "2023-06-10",
      "motherSlotTime": "10:15 AM",
      "motherSlotLocation": "Mumbai",
      "userVacStatus": "no",
      "fatherVacStatus": "no",
      "motherVacStatus": "no",
      "confirmPassword": "Hassin@123",
      "id": 20
    },
    {
      "username": "abcde",
      "email": "abcde@1213.dv",
      "password": "Abcde@123",
      "age": 12,
      "phone": 1234865321,
      "fathername": "seagsG",
      "mothername": "fdzhnhgf",
      "fatherAge": 44,
      "motherAge": 30,
      "isAdmin": "false",
      "userSlotBooked": "no",
      "userSlotDate": "no",
      "userSlotTime": "no",
      "userSlotLocation": "",
      "fatherSlotBooked": "no",
      "fatherSlotDate": "no",
      "fatherSlotTime": "no",
      "fatherSlotLocation": "",
      "motherSlotBooked": "no",
      "motherSlotDate": "no",
      "motherSlotTime": "no",
      "motherSlotLocation": "",
      "userVacStatus": "no",
      "fatherVacStatus": "no",
      "motherVacStatus": "no",
      "address": "fzdhzdh,.mdnhm,d dfg",
      "confirmPassword": "Abcde@123",
      "id": 21
    }
  ]
}